app.py
mcp_api_call.py
iflow_mcp_gradio_mcp_agent_hack-0.2.0.dist-info/licenses/LICENSE
mcp_hub/__init__.py
mcp_hub/advanced_config.py
mcp_hub/async_utils.py
mcp_hub/cache_utils.py
mcp_hub/config.py
mcp_hub/exceptions.py
mcp_hub/health_monitoring.py
mcp_hub/logging_config.py
mcp_hub/package_utils.py
mcp_hub/performance_monitoring.py
mcp_hub/reliability_utils.py
mcp_hub/sandbox_pool.py
mcp_hub/utils.py
iflow_mcp_gradio_mcp_agent_hack-0.2.0.dist-info/METADATA
iflow_mcp_gradio_mcp_agent_hack-0.2.0.dist-info/WHEEL
iflow_mcp_gradio_mcp_agent_hack-0.2.0.dist-info/entry_points.txt
iflow_mcp_gradio_mcp_agent_hack-0.2.0.dist-info/top_level.txt
iflow_mcp_gradio_mcp_agent_hack-0.2.0.dist-info/RECORD
