Metadata-Version: 2.4
Name: iflow-mcp_gradio-mcp-agent-hack
Version: 0.2.0
Summary: Advanced MCP Hub with Inter-Agent Communication and Performance Monitoring
Requires-Python: >=3.12
License-File: LICENSE
Requires-Dist: gradio-client>=1.10.2
Requires-Dist: gradio[mcp]>=5.33.0
Requires-Dist: modal>=1.0.2
Requires-Dist: openai>=1.84.0
Requires-Dist: tavily-python>=0.7.4
Requires-Dist: python-dotenv>=1.0.0
Requires-Dist: psutil>=5.9.0
Requires-Dist: aiohttp>=3.8.0
Requires-Dist: anthropic>=0.52.2
Requires-Dist: huggingface>=0.0.1
Requires-Dist: huggingface-hub>=0.32.4
Provides-Extra: dev
Requires-Dist: pytest>=7.4.0; extra == "dev"
Requires-Dist: pytest-cov>=4.1.0; extra == "dev"
Requires-Dist: black>=23.0.0; extra == "dev"
Requires-Dist: isort>=5.12.0; extra == "dev"
Requires-Dist: mypy>=1.5.0; extra == "dev"
Dynamic: license-file
